README.txt
setup.py
Products/__init__.py
Products.PloneboardComments.egg-info/PKG-INFO
Products.PloneboardComments.egg-info/SOURCES.txt
Products.PloneboardComments.egg-info/dependency_links.txt
Products.PloneboardComments.egg-info/entry_points.txt
Products.PloneboardComments.egg-info/namespace_packages.txt
Products.PloneboardComments.egg-info/not-zip-safe
Products.PloneboardComments.egg-info/requires.txt
Products.PloneboardComments.egg-info/top_level.txt
Products/PloneboardComments/BUGS.txt
Products/PloneboardComments/CHANGES.txt
Products/PloneboardComments/Makefile
Products/PloneboardComments/README.txt
Products/PloneboardComments/__init__.py
Products/PloneboardComments/comments.pt
Products/PloneboardComments/comments.py
Products/PloneboardComments/comments.py.oldcode
Products/PloneboardComments/config.py
Products/PloneboardComments/configure.zcml
Products/PloneboardComments/overrides.zcml
Products/PloneboardComments/browser/__init__.py
Products/PloneboardComments/browser/configure.zcml
Products/PloneboardComments/browser/overrides.zcml
Products/PloneboardComments/content/PloneboardComments.py
Products/PloneboardComments/content/__init__.py
Products/PloneboardComments/content/configure.zcml
Products/PloneboardComments/content/interfaces.py
Products/PloneboardComments/i18n/PloneComments-no.mo
Products/PloneboardComments/i18n/PloneComments-no.po
Products/PloneboardComments/interfaces/__init__.py
Products/PloneboardComments/overrides/__init__.py
Products/PloneboardComments/overrides/quills_entry_macros.pt
Products/PloneboardComments/portlets/__init__.py
Products/PloneboardComments/portlets/configure.zcml
Products/PloneboardComments/profiles/default/factorytool.xml
Products/PloneboardComments/profiles/default/metadata.xml
Products/PloneboardComments/profiles/default/portlets.xml
Products/PloneboardComments/profiles/default/skins.xml
Products/PloneboardComments/profiles/default/types.xml
Products/PloneboardComments/profiles/default/types/PloneboardComments.xml
Products/PloneboardComments/skins/PloneboardComments/ploneboard_comments_create_conversation_url.cpy
Products/PloneboardComments/skins/PloneboardComments/ploneboard_comments_create_conversation_url.cpy.metadata
Products/PloneboardComments/skins/PloneboardComments/ploneboard_comments_get_conversation.cpy
Products/PloneboardComments/skins/PloneboardComments/ploneboard_comments_get_conversation.cpy.metadata
