Metadata-Version: 1.0
Name: Products.PloneboardComments
Version: 1.0.4
Summary: Tool for connecting Ploneboard to content, to make it discussable in Ploneboard forums
Home-page: http://www.nidelven-it.no/d
Author: Morten W. Petersen
Author-email: info@nidelven-it.no
License: GPL
Keywords: python plone ploneboard discussion
Platform: UNKNOWN
Classifier: Programming Language :: Python
